esprit/__init__.py
esprit/agents/EspritAgent/__init__.py
esprit/agents/EspritAgent/esprit_agent.py
esprit/agents/EspritAgent/system_prompt.jinja
esprit/agents/__init__.py
esprit/agents/base_agent.py
esprit/agents/state.py
esprit/auth/__init__.py
esprit/auth/client.py
esprit/auth/commands.py
esprit/auth/credentials.py
esprit/interface/__init__.py
esprit/interface/assets/tui_styles.tcss
esprit/interface/cli.py
esprit/interface/main.py
esprit/interface/tool_components/__init__.py
esprit/interface/tool_components/agents_graph_renderer.py
esprit/interface/tool_components/base_renderer.py
esprit/interface/tool_components/browser_renderer.py
esprit/interface/tool_components/file_edit_renderer.py
esprit/interface/tool_components/finish_renderer.py
esprit/interface/tool_components/message_formatter.py
esprit/interface/tool_components/notes_renderer.py
esprit/interface/tool_components/proxy_renderer.py
esprit/interface/tool_components/python_renderer.py
esprit/interface/tool_components/registry.py
esprit/interface/tool_components/reporting_renderer.py
esprit/interface/tool_components/scan_info_renderer.py
esprit/interface/tool_components/terminal_renderer.py
esprit/interface/tool_components/thinking_renderer.py
esprit/interface/tool_components/user_message_renderer.py
esprit/interface/tool_components/web_search_renderer.py
esprit/interface/tui.py
esprit/interface/utils.py
esprit/llm/__init__.py
esprit/llm/config.py
esprit/llm/llm.py
esprit/llm/memory_compressor.py
esprit/llm/request_queue.py
esprit/llm/utils.py
esprit/prompts/README.md
esprit/prompts/__init__.py
esprit/prompts/cloud/.gitkeep
esprit/prompts/coordination/root_agent.jinja
esprit/prompts/custom/.gitkeep
esprit/prompts/frameworks/fastapi.jinja
esprit/prompts/frameworks/nextjs.jinja
esprit/prompts/protocols/graphql.jinja
esprit/prompts/reconnaissance/.gitkeep
esprit/prompts/technologies/firebase_firestore.jinja
esprit/prompts/technologies/supabase.jinja
esprit/prompts/vulnerabilities/authentication_jwt.jinja
esprit_cli-0.5.2.dist-info/METADATA
esprit_cli-0.5.2.dist-info/WHEEL
esprit_cli-0.5.2.dist-info/entry_points.txt
esprit_cli-0.5.2.dist-info/RECORD
