Metadata-Version: 2.4
Name: esprit-cli
Version: 0.5.2
Summary: AI-Powered Penetration Testing CLI
License: Apache-2.0
Keywords: cybersecurity,security,vulnerability,scanner,pentest,penetration-testing,agent,ai,cli
Author: Esprit Security
Author-email: support@esprit.dev
Requires-Python: >=3.11,<4.0
Classifier: Development Status :: 4 - Beta
Classifier: Environment :: Console
Classifier: Intended Audience :: Developers
Classifier: Intended Audience :: Information Technology
Classifier: Intended Audience :: System Administrators
Classifier: License :: OSI Approved :: Apache Software License
Classifier: Programming Language :: Python
Classifier: Programming Language :: Python :: 3
Classifier: Programming Language :: Python :: 3.11
Classifier: Programming Language :: Python :: 3.12
Classifier: Programming Language :: Python :: 3.13
Classifier: Programming Language :: Python :: 3.14
Classifier: Programming Language :: Python :: 3 :: Only
Classifier: Topic :: Security
Requires-Dist: requests (>=2.32.0,<3.0.0)
Requires-Dist: rich (>=14.0.0,<15.0.0)
Project-URL: Documentation, https://esprit.dev/docs
Project-URL: Homepage, https://esprit.dev
Project-URL: Repository, https://github.com/esprit-security/esprit
